ypy_websocket/__init__.py
ypy_websocket/asgi_server.py
ypy_websocket/awareness.py
ypy_websocket/django_channels_consumer.py
ypy_websocket/py.typed
ypy_websocket/websocket.py
ypy_websocket/websocket_provider.py
ypy_websocket/websocket_server.py
ypy_websocket/yroom.py
ypy_websocket/ystore.py
ypy_websocket/yutils.py
ypy_websocket-0.12.3.dist-info/METADATA
ypy_websocket-0.12.3.dist-info/WHEEL
ypy_websocket-0.12.3.dist-info/licenses/LICENSE
ypy_websocket-0.12.3.dist-info/RECORD
