Metadata-Version: 2.1
Name: ypy-websocket
Version: 0.12.3
Summary: WebSocket connector for Ypy
Project-URL: Homepage, https://github.com/y-crdt/ypy-websocket
Project-URL: Source, https://github.com/y-crdt/ypy-websocket
Project-URL: Issues, https://github.com/y-crdt/ypy-websocket/issues
Project-URL: Pypi, https://pypi.org/project/ypy-websocket
Author-email: David Brochart <david.brochart@gmail.com>
License: MIT License
License-File: LICENSE
Keywords: websocket,yjs
Classifier: Development Status :: 4 - Beta
Classifier: Intended Audience :: Developers
Classifier: License :: OSI Approved :: MIT License
Classifier: Programming Language :: Python
Classifier: Programming Language :: Python :: 3.7
Classifier: Programming Language :: Python :: 3.8
Classifier: Programming Language :: Python :: 3.9
Classifier: Programming Language :: Python :: 3.10
Classifier: Programming Language :: Python :: 3.11
Requires-Python: >=3.7
Requires-Dist: aiosqlite<1,>=0.18.0
Requires-Dist: anyio<5,>=3.6.2
Requires-Dist: typing-extensions; python_version < '3.8'
Requires-Dist: y-py<0.7.0,>=0.6.0
Provides-Extra: django
Requires-Dist: channels; extra == 'django'
Provides-Extra: docs
Requires-Dist: mkdocs; extra == 'docs'
Requires-Dist: mkdocs-material; extra == 'docs'
Requires-Dist: mkdocstrings-python; extra == 'docs'
Provides-Extra: test
Requires-Dist: mypy; extra == 'test'
Requires-Dist: pre-commit; extra == 'test'
Requires-Dist: pytest; extra == 'test'
Requires-Dist: pytest-asyncio; extra == 'test'
Requires-Dist: uvicorn; extra == 'test'
Requires-Dist: websockets>=10.0; extra == 'test'
